README.md
data/ISM-OHM.dat
data/instruments.csv
data/pupils.csv
data/pupils.json
hypercat/__init__.py
hypercat/hypercat.py
hypercat/imageops.py
hypercat/interferometry.py
hypercat/ioops.py
hypercat/loggers.py
hypercat/morphology.py
hypercat/ndiminterpolation.py
hypercat/obsmodes.py
hypercat/plotting.py
hypercat/psf.py
hypercat/scripts.py
hypercat/units.py
hypercat/utils.py
hypercatgui/__init__.py
hypercatgui/hypercatgui.py
rgb.png
hypercat-0.1.11.dist-info/entry_points.txt
hypercat-0.1.11.dist-info/LICENSE
hypercat-0.1.11.dist-info/WHEEL
hypercat-0.1.11.dist-info/METADATA
hypercat-0.1.11.dist-info/RECORD
