Metadata-Version: 2.1
Name: hypercat
Version: 0.1.11
Summary: Hypercube of clumpy AGN tori
Home-page: https://github.com/rnikutta/hypercat
License: BSD-3-Clause
Keywords: astronomy,active galactic nuclei,hypercubes,extremely large telescopes,morphology
Author: Robert Nikutta
Author-email: robert.nikutta@gmail.com
Requires-Python: >=3.7.2
Classifier: Development Status :: 4 - Beta
Classifier: Intended Audience :: Science/Research
Classifier: License :: OSI Approved :: BSD License
Classifier: Operating System :: OS Independent
Classifier: Programming Language :: Python :: 3
Classifier: Programming Language :: Python :: 3.8
Classifier: Programming Language :: Python :: 3.9
Classifier: Topic :: Scientific/Engineering :: Astronomy
Requires-Dist: astropy
Requires-Dist: h5py (==2.9.0)
Requires-Dist: ipython (>=7.24.1,<8.0.0)
Requires-Dist: jupyterlab (>=3.0.16,<4.0.0)
Requires-Dist: matplotlib
Requires-Dist: numpy
Requires-Dist: pandas (>=1.2.4,<2.0.0)
Requires-Dist: scikit-image
Requires-Dist: scipy
Requires-Dist: urwid (>=2.0.1)
Project-URL: Repository, https://github.com/rnikutta/hypercat
